aemuctrl.py
aemuctrl-0.1.0.dist-info/LICENCE
aemuctrl-0.1.0.dist-info/METADATA
aemuctrl-0.1.0.dist-info/WHEEL
aemuctrl-0.1.0.dist-info/top_level.txt
aemuctrl-0.1.0.dist-info/RECORD
