Metadata-Version: 2.1
Name: aemuctrl
Version: 0.1.0
Summary: A lightweight Android Emulator Control library using ADB and PyAutoGUI
Home-page: https://github.com/Solee-in/aemuctrl
Author: Your Name
License: MIT
Classifier: Programming Language :: Python :: 3
Classifier: License :: OSI Approved :: MIT License
Classifier: Operating System :: Microsoft :: Windows
Classifier: Operating System :: MacOS
Classifier: Topic :: Software Development :: Libraries :: Python Modules
Requires-Python: >=3.6
License-File: LICENCE
Requires-Dist: pyautogui
